[{"name":"American Albino","id":1},{"name":"Abaco Barb","id":2},{"name":"Abtenauer","id":3},{"name":"Abyssinian","id":4},{"name":"Aegidienberger","id":5},{"name":"Akhal-Teke","id":6},{"name":"Albanian Horse","id":7},{"name":"Altai Horse","id":8},{"name":"Altèr Real","id":9},{"name":"American Cream Draft","id":10},{"name":"American Indian Horse","id":11},{"name":"American Paint Horse","id":12},{"name":"American Quarter Horse","id":13},{"name":"American Saddlebred","id":14},{"name":"American Warmblood","id":15},{"name":"Andalusian Horse","id":16},{"name":"Andravida Horse","id":17},{"name":"Anglo-Arabian","id":18},{"name":"Anglo-Arabo-Sardo","id":19},{"name":"Anglo-Kabarda","id":20},{"name":"Appaloosa","id":21},{"name":"AraAppaloosa","id":22},{"name":"Arabian Horse","id":23},{"name":"Ardennes Horse","id":24},{"name":"Arenberg-Nordkirchen","id":25},{"name":"Argentine Criollo","id":26},{"name":"Asian wild Horse","id":27},{"name":"Assateague Horse","id":28},{"name":"Asturcón","id":29},{"name":"Augeron","id":30},{"name":"Australian Brumby","id":31},{"name":"Australian Draught Horse","id":32},{"name":"Australian Stock Horse","id":33},{"name":"Austrian Warmblood","id":34},{"name":"Auvergne Horse","id":35},{"name":"Auxois","id":36},{"name":"Azerbaijan Horse","id":37},{"name":"Azteca Horse","id":38},{"name":"Baise Horse","id":39},{"name":"Bale","id":40},{"name":"Balearic Horse","id":41},{"name":"Balikun Horse","id":42},{"name":"Baluchi Horse","id":43},{"name":"Banker Horse","id":44},{"name":"Barb Horse","id":45},{"name":"Bardigiano","id":46},{"name":"Bashkir Curly","id":47},{"name":"Basque Mountain Horse","id":48},{"name":"Bavarian Warmblood","id":49},{"name":"Belgian Half-blood","id":50},{"name":"Belgian Horse","id":51},{"name":"Belgian Warmblood ","id":52},{"name":"Bhutia Horse","id":53},{"name":"Black Forest Horse","id":54},{"name":"Blazer Horse","id":55},{"name":"Boerperd","id":56},{"name":"Borana","id":57},{"name":"Boulonnais Horse","id":58},{"name":"Brabant","id":59},{"name":"Brandenburger","id":60},{"name":"Brazilian Sport Horse","id":61},{"name":"Breton Horse","id":62},{"name":"Brumby","id":63},{"name":"Budyonny Horse","id":64},{"name":"Burguete Horse","id":65},{"name":"Burmese Horse","id":66},{"name":"Byelorussian Harness Horse","id":67},{"name":"Calabrese Horse","id":68},{"name":"Camargue Horse","id":69},{"name":"Camarillo White Horse","id":70},{"name":"Campeiro","id":71},{"name":"Campolina","id":72},{"name":"Canadian Horse","id":73},{"name":"Canadian Pacer","id":74},{"name":"Carolina Marsh Tacky","id":75},{"name":"Carthusian Horse","id":76},{"name":"Caspian Horse","id":77},{"name":"Castilian Horse","id":78},{"name":"Castillonnais","id":79},{"name":"Catria Horse","id":80},{"name":"Cavallo Romano della Maremma Laziale","id":81},{"name":"Cerbat Mustang","id":82},{"name":"Chickasaw Horse","id":83},{"name":"Chilean Corralero","id":84},{"name":"Choctaw Horse","id":85},{"name":"Cleveland Bay","id":86},{"name":"Clydesdale Horse","id":87},{"name":"Cob","id":88},{"name":"Coldblood Trotter","id":89},{"name":"Colonial Spanish Horse","id":90},{"name":"Colorado Ranger","id":91},{"name":"Comtois Horse","id":92},{"name":"Corsican Horse","id":93},{"name":"Costa Rican Saddle Horse","id":94},{"name":"Cretan Horse","id":95},{"name":"Criollo Horse","id":96},{"name":"Croatian Coldblood","id":97},{"name":"Cuban Criollo","id":98},{"name":"Cumberland Island Horse","id":99},{"name":"Curly Horse","id":100},{"name":"Czech Warmblood","id":101},{"name":"Daliboz","id":102},{"name":"Danish Warmblood","id":103},{"name":"Danube Delta Horse","id":104},{"name":"Dole Gudbrandsdal","id":105},{"name":"Don","id":106},{"name":"Dongola Horse","id":107},{"name":"Draft Trotter","id":108},{"name":"Dutch Harness Horse","id":109},{"name":"Dutch Heavy Draft","id":110},{"name":"Dutch Warmblood","id":111},{"name":"Dzungarian Horse","id":112},{"name":"East Bulgarian","id":113},{"name":"East Friesian Horse","id":114},{"name":"Estonian Draft","id":115},{"name":"Estonian Horse","id":116},{"name":"Falabella","id":117},{"name":"Faroese","id":118},{"name":"Finnhorse","id":119},{"name":"Fjord Horse","id":120},{"name":"Fleuve","id":121},{"name":"Florida Cracker Horse","id":122},{"name":"Foutanké","id":123},{"name":"Frederiksborg Horse","id":124},{"name":"Freiberger","id":125},{"name":"French Trotter","id":126},{"name":"Friesian Cross","id":127},{"name":"Friesian Horse","id":128},{"name":"Friesian Sporthorse","id":129},{"name":"Furioso-North Star","id":130},{"name":"Galiceño","id":131},{"name":"Galician Pony","id":132},{"name":"Gelderland Horse","id":133},{"name":"Georgian Grande Horse","id":134},{"name":"German Warmblood","id":135},{"name":"Giara Horse","id":136},{"name":"Gidran","id":137},{"name":"Groningen Horse","id":138},{"name":"Gypsy Horse","id":139},{"name":"Hackney Horse","id":140},{"name":"Haflinger","id":141},{"name":"Hanoverian Horse","id":142},{"name":"Heck Horse","id":143},{"name":"Heihe Horse","id":144},{"name":"Henson Horse","id":145},{"name":"Hequ Horse","id":146},{"name":"Hirzai","id":147},{"name":"Hispano-Bretón","id":148},{"name":"Holsteiner Horse","id":149},{"name":"Horro","id":150},{"name":"Hungarian Warmblood","id":151},{"name":"Icelandic Horse","id":152},{"name":"Iomud","id":153},{"name":"Irish Draught","id":154},{"name":"Irish Sport Horse sometimes called Irish Hunter","id":155},{"name":"Italian Heavy Draft","id":156},{"name":"Italian Trotter","id":157},{"name":"Jaca Navarra","id":158},{"name":"Jeju Horse","id":159},{"name":"Jutland Horse","id":160},{"name":"Kabarda Horse","id":161},{"name":"Kafa","id":162},{"name":"Kaimanawa Horses","id":163},{"name":"Kalmyk Horse","id":164},{"name":"Karabair","id":165},{"name":"Karabakh Horse","id":166},{"name":"Karachai Horse","id":167},{"name":"Karossier","id":168},{"name":"Kathiawari","id":169},{"name":"Kazakh Horse","id":170},{"name":"Kentucky Mountain Saddle Horse","id":171},{"name":"Kiger Mustang","id":172},{"name":"Kinsky Horse","id":173},{"name":"Kisber Felver","id":174},{"name":"Kiso Horse","id":175},{"name":"Kladruber","id":176},{"name":"Knabstrupper","id":177},{"name":"Konik","id":178},{"name":"Kundudo","id":179},{"name":"Kustanair","id":180},{"name":"Kyrgyz Horse","id":181},{"name":"Latvian Horse","id":182},{"name":"Lipizzan","id":183},{"name":"Lithuanian Heavy Draught","id":184},{"name":"Lokai","id":185},{"name":"Losino Horse","id":186},{"name":"Lusitano","id":187},{"name":"Lyngshest","id":188},{"name":"M'Bayar","id":189},{"name":"M'Par","id":190},{"name":"Mallorquín","id":191},{"name":"Malopolski","id":192},{"name":"Mangalarga","id":193},{"name":"Mangalarga Marchador","id":194},{"name":"Maremmano","id":195},{"name":"Marismeño Horse","id":196},{"name":"Marsh Tacky","id":197},{"name":"Marwari Horse","id":198},{"name":"Mecklenburger","id":199},{"name":"Međimurje Horse","id":200},{"name":"Menorquín","id":201},{"name":"Mérens Horse","id":202},{"name":"Messara Horse","id":203},{"name":"Metis Trotter","id":204},{"name":"Mezőhegyesi Sport Horse","id":205},{"name":"Miniature Horse","id":206},{"name":"Misaki Horse","id":207},{"name":"Missouri Fox Trotter","id":208},{"name":"Monchina","id":209},{"name":"Mongolian Horse","id":210},{"name":"Mongolian Wild Horse","id":211},{"name":"Monterufolino","id":212},{"name":"Morab","id":213},{"name":"Morgan Horse","id":214},{"name":"Mountain Pleasure Horse","id":215},{"name":"Moyle Horse","id":216},{"name":"Murakoz Horse","id":217},{"name":"Murgese","id":218},{"name":"Mustang Horse","id":219},{"name":"Namib Desert Horse","id":220},{"name":"Nangchen Horse","id":221},{"name":"National Show Horse","id":222},{"name":"Nez Perce Horse","id":223},{"name":"Nivernais Horse","id":224},{"name":"Nokota Horse","id":225},{"name":"Noma","id":226},{"name":"Nonius Horse","id":227},{"name":"Nooitgedachter","id":228},{"name":"Nordlandshest","id":229},{"name":"Noriker Horse","id":230},{"name":"Norman Cob","id":231},{"name":"North American Single-Footer Horse","id":232},{"name":"North Swedish Horse","id":233},{"name":"Norwegian Coldblood Trotter","id":234},{"name":"Norwegian Fjord","id":235},{"name":"Novokirghiz","id":236},{"name":"Oberlander Horse","id":237},{"name":"Ogaden","id":238},{"name":"Oldenburg Horse","id":239},{"name":"Orlov trotter","id":240},{"name":"Ostfriesen","id":241},{"name":"Paint","id":242},{"name":"Pampa Horse","id":243},{"name":"Paso Fino","id":244},{"name":"Pentro Horse","id":245},{"name":"Percheron","id":246},{"name":"Persano Horse","id":247},{"name":"Peruvian Paso","id":248},{"name":"Pintabian","id":249},{"name":"Pleven Horse","id":250},{"name":"Poitevin Horse","id":251},{"name":"Posavac Horse","id":252},{"name":"Pottok","id":253},{"name":"Pryor Mountain Mustang","id":254},{"name":"Przewalski's Horse","id":255},{"name":"Pura Raza Española","id":256},{"name":"Purosangue Orientale","id":257},{"name":"Qatgani","id":258},{"name":"Quarab","id":259},{"name":"Quarter Horse","id":260},{"name":"Racking Horse","id":261},{"name":"Retuerta Horse","id":262},{"name":"Rhenish German Coldblood","id":263},{"name":"Rhinelander Horse","id":264},{"name":"Riwoche Horse","id":265},{"name":"Rocky Mountain Horse","id":266},{"name":"Romanian Sporthorse","id":267},{"name":"Rottaler","id":268},{"name":"Russian Don","id":269},{"name":"Russian Heavy Draft","id":270},{"name":"Russian Trotter","id":271},{"name":"Saddlebred","id":272},{"name":"Salerno Horse","id":273},{"name":"Samolaco Horse","id":274},{"name":"San Fratello Horse","id":275},{"name":"Sarcidano Horse","id":276},{"name":"Sardinian Anglo-Arab","id":277},{"name":"Schleswig Coldblood","id":278},{"name":"Schwarzwälder Kaltblut","id":279},{"name":"Selale","id":280},{"name":"Sella Italiano","id":281},{"name":"Selle Français","id":282},{"name":"Shagya Arabian","id":283},{"name":"Shan Horse","id":284},{"name":"Shire Horse","id":285},{"name":"Siciliano Indigeno","id":286},{"name":"Silesian Horse","id":287},{"name":"Sokolsky Horse","id":288},{"name":"Sorraia","id":289},{"name":"South German Coldblood","id":290},{"name":"Soviet Heavy Draft","id":291},{"name":"Spanish Anglo-Arab","id":292},{"name":"Spanish Barb","id":293},{"name":"Spanish Jennet Horse","id":294},{"name":"Spanish Mustang","id":295},{"name":"Spanish Tarpan","id":296},{"name":"Spanish-Norman Horse","id":297},{"name":"Spiti Horse","id":298},{"name":"Spotted Saddle Horse","id":299},{"name":"Standardbred Horse","id":300},{"name":"Suffolk Punch","id":301},{"name":"Swedish Ardennes","id":302},{"name":"Swedish coldblood trotter","id":303},{"name":"Swedish Warmblood","id":304},{"name":"Swiss Warmblood","id":305},{"name":"Taishū Horse","id":306},{"name":"Takhi","id":307},{"name":"Tawleed","id":308},{"name":"Tchernomor","id":309},{"name":"Tennessee Walking Horse","id":310},{"name":"Tersk Horse","id":311},{"name":"Thoroughbred","id":312},{"name":"Tiger Horse","id":313},{"name":"Tinker Horse","id":314},{"name":"Tolfetano","id":315},{"name":"Tori Horse","id":316},{"name":"Trait Du Nord","id":317},{"name":"Trakehner","id":318},{"name":"Tsushima","id":319},{"name":"Tuigpaard","id":320},{"name":"Ukrainian Riding Horse","id":321},{"name":"Unmol Horse","id":322},{"name":"Uzunyayla","id":323},{"name":"Ventasso Horse","id":324},{"name":"Virginia Highlander","id":325},{"name":"Vlaamperd","id":326},{"name":"Vladimir Heavy Draft","id":327},{"name":"Vyatka","id":328},{"name":"Waler","id":329},{"name":"Waler Horse","id":330},{"name":"Walkaloosa","id":331},{"name":"Warlander","id":332},{"name":"Warmblood","id":333},{"name":"Welsh Cob","id":334},{"name":"Westphalian Horse","id":335},{"name":"Wielkopolski","id":336},{"name":"Württemberger","id":337},{"name":"Xilingol Horse","id":338},{"name":"Yakutian Horse","id":339},{"name":"Yili Horse","id":340},{"name":"Yonaguni Horse","id":341},{"name":"Zaniskari","id":342},{"name":"Žemaitukas","id":343},{"name":"Zhemaichu","id":344},{"name":"Zweibrücker","id":345}]